request_logger/__init__.py
request_logger/apps.py
request_logger/middleware.py
request_logger/models.py
request_logger/routers.py
request_logger/migrations/0001_initial.py
request_logger/migrations/0001_squashed_0003_auto_20171115_1506.py
request_logger/migrations/0002_auto_20170918_1506.py
request_logger/migrations/0003_auto_20171115_1506.py
request_logger/migrations/__init__.py
django_request_logger-0.2.0.dist-info/LICENSE
django_request_logger-0.2.0.dist-info/METADATA
django_request_logger-0.2.0.dist-info/WHEEL
django_request_logger-0.2.0.dist-info/top_level.txt
django_request_logger-0.2.0.dist-info/RECORD
