Metadata-Version: 2.1
Name: django-request-logger
Version: 0.2.0
Summary: Django middleware that logs http request information to database.
Home-page: https://git.pispalanit.fi/pit/django-request-logger
Author: Joni Saarinen
Author-email: joni.saarinen@pispalanit.fi
License: MIT
Platform: UNKNOWN
Classifier: Programming Language :: Python :: 3.6
Classifier: Operating System :: POSIX :: Linux
Requires-Dist: Django
